dashboard_pyechart/__init__.py
dashboard_pyechart/core.py
dashboard_pyechart/css.py
dashboard_pyechart/template.py
dashboard_pyechart-0.0.2.dist-info/DESCRIPTION.rst
dashboard_pyechart-0.0.2.dist-info/METADATA
dashboard_pyechart-0.0.2.dist-info/RECORD
dashboard_pyechart-0.0.2.dist-info/WHEEL
dashboard_pyechart-0.0.2.dist-info/metadata.json
dashboard_pyechart-0.0.2.dist-info/top_level.txt
