Metadata-Version: 2.0
Name: dashboard-pyechart
Version: 0.0.2
Summary: A easy dashboard package
Home-page: UNKNOWN
Author: Jason Rao
Author-email: raotl1995@gmail.com
License: UNKNOWN
Platform: UNKNOWN
Classifier: Programming Language :: Python :: 3
Classifier: License :: OSI Approved :: Common Public License
Classifier: Operating System :: Microsoft
